HandTracking/__init__.py
HandTracking-0.3.dist-info/Licence.txt.txt
HandTracking-0.3.dist-info/METADATA
HandTracking-0.3.dist-info/WHEEL
HandTracking-0.3.dist-info/top_level.txt
HandTracking-0.3.dist-info/RECORD
