Metadata-Version: 1.0
Name: HandTracking
Version: 0.3
Summary: This is HandTracking package made by abhinav kourav.
Home-page: UNKNOWN
Author: Abhinav Kourav
Author-email: kouabhinav@gmail.com
License: UNKNOWN
Platform: UNKNOWN
